MANIFEST.in
README.md
dev.txt
pandas.txt
requirements.txt
setup.py
quarrel/__init__.py
quarrel/_version.py
quarrel/connections.py
quarrel/settings.py
quarrel.egg-info/PKG-INFO
quarrel.egg-info/SOURCES.txt
quarrel.egg-info/dependency_links.txt
quarrel.egg-info/requires.txt
quarrel.egg-info/top_level.txt
quarrel/cooked/__init__.py
quarrel/pandas/__init__.py
quarrel/raw/__init__.py
quarrel/sqlalchemy/__init__.py
quarrel/templates/__init__.py